{
  "id": "agile",
  "name": "Agile Delivery",
  "slug": "agile",
  "description": "Applying iterative delivery principles, stakeholder collaboration and adaptive planning within technical projects.",
  "discipline": "delivery",
  "category": [
    "methodology",
    "leadership",
    "operational",
    "strategic"
  ],
  "featured": false,
  "visibility": "public",
  "relatedDomains": [
    "programme-management",
    "digital-transformation",
    "business-transformation",
    "project-management",
    "software-dev",
    "service-transition"
  ]
}